{
    "relaxed-crystal": {
        "key": "251fe162-11b7-494a-b4b3-64384f0b6307",
        "URL": "https://potentials.nist.gov/pid/rest/local/potentials/251fe162-11b7-494a-b4b3-64384f0b6307",
        "method": "static",
        "standing": "bad",
        "potential-LAMMPS": {
            "key": "MO_903987585848_003",
            "id": "Tersoff_LAMMPS_ErhartAlbe_2005_SiC__MO_903987585848_003",
            "URL": "https://potentials.nist.gov/pid/rest/local/potentials/MO_903987585848",
            "potential": {
                "key": "f4088e3f-65ec-419d-a677-b5f533f984d0",
                "id": "2005--Erhart-P-Albe-K--Si-C-I",
                "URL": "https://potentials.nist.gov/pid/rest/local/potentials/potential.2005--Erhart-P-Albe-K--Si-C-I"
            }
        },
        "system-info": {
            "family": "mp-1095269",
            "family-URL": "https://potentials.nist.gov/pid/rest/local/potentials/mp-1095269",
            "parent_key": "5d864f57-ea55-490c-ad48-f1618e958c77",
            "symbol": "Si",
            "composition": "Si",
            "cell": {
                "crystal-family": "orthorhombic",
                "natypes": 1,
                "a": 3.79997901317377,
                "b": 11.05592739123136,
                "c": 12.443418136824,
                "alpha": 90.0,
                "beta": 90.0,
                "gamma": 90.0
            }
        },
        "atomic-system": {
            "box": {
                "avect": {
                    "value": [
                        3.79997901317377,
                        0.0,
                        0.0
                    ],
                    "unit": "angstrom"
                },
                "bvect": {
                    "value": [
                        0.0,
                        11.05592739123136,
                        0.0
                    ],
                    "unit": "angstrom"
                },
                "cvect": {
                    "value": [
                        0.0,
                        0.0,
                        12.443418136824
                    ],
                    "unit": "angstrom"
                },
                "origin": {
                    "value": [
                        0.0,
                        0.0,
                        0.0
                    ],
                    "unit": "angstrom"
                }
            },
            "periodic-boundary-condition": [
                true,
                true,
                true
            ],
            "atom-type-symbol": "Si",
            "atoms": {
                "natoms": 24,
                "property": [
                    {
                        "name": "atype",
                        "data": {
                            "value": [
                                1,
                                1,
                                1,
                                1,
                                1,
                                1,
                                1,
                                1,
                                1,
                                1,
                                1,
                                1,
                                1,
                                1,
                                1,
                                1,
                                1,
                                1,
                                1,
                                1,
                                1,
                                1,
                                1,
                                1
                            ]
                        }
                    },
                    {
                        "name": "pos",
                        "data": {
                            "value": [
                                0.0,
                                0.0,
                                0.0,
                                1.8999895065868855,
                                0.19064836976175137,
                                1.413376850210451,
                                0.0,
                                0.0,
                                7.635085918622452,
                                1.8999895065868855,
                                0.19064836976175137,
                                6.221709068412,
                                1.8999895065868855,
                                9.180408004851644,
                                2.6342297793873684,
                                0.0,
                                2.0661677561414677,
                                11.222565207647083,
                                1.8999895065868855,
                                9.180408004851644,
                                5.000856139235083,
                                0.0,
                                2.0661677561414677,
                                8.85593884779937,
                                0.0,
                                8.71164151336112,
                                12.028467244258602,
                                0.0,
                                8.062897943247673,
                                1.8283277427758475,
                                0.0,
                                8.71164151336112,
                                8.05003681118785,
                                0.0,
                                8.062897943247673,
                                5.806758175846603,
                                1.8999895065868855,
                                5.527963695615681,
                                0.0,
                                0.0,
                                5.71861206537743,
                                1.413376850210451,
                                1.8999895065868855,
                                5.527963695615681,
                                7.635085918622452,
                                0.0,
                                5.71861206537743,
                                6.221709068412,
                                0.0,
                                3.6524443092359657,
                                2.6342297793873684,
                                1.8999895065868855,
                                7.594131451757147,
                                11.222565207647083,
                                0.0,
                                3.6524443092359657,
                                5.000856139235083,
                                1.8999895065868855,
                                7.594131451757147,
                                8.85593884779937,
                                1.8999895065868855,
                                3.1836778177454397,
                                12.028467244258602,
                                1.8999895065868855,
                                2.534934247631993,
                                1.8283277427758475,
                                1.8999895065868855,
                                3.1836778177454397,
                                8.05003681118785,
                                1.8999895065868855,
                                2.534934247631993,
                                5.806758175846603
                            ],
                            "shape": [
                                24,
                                3
                            ],
                            "unit": "angstrom"
                        }
                    }
                ]
            }
        },
        "potential-energy": {
            "value": -4.4286990734512495,
            "unit": "eV"
        },
        "cohesive-energy": {
            "value": -4.4286990734512495,
            "unit": "eV"
        }
    }
}