{
    "relaxed-crystal": {
        "key": "96f040d7-fcd8-4780-9e37-e272b749b738",
        "URL": "https://potentials.nist.gov/pid/rest/local/potentials/96f040d7-fcd8-4780-9e37-e272b749b738",
        "method": "box",
        "standing": "good",
        "potential-LAMMPS": {
            "key": "7a0fc5db-0c9f-44f0-a005-4d6d6862a7aa",
            "id": "1989--Tersoff-J--Si-Ge--LAMMPS--ipr1",
            "URL": "https://potentials.nist.gov/pid/rest/local/potentials/1989--Tersoff-J--Si-Ge--LAMMPS--ipr1",
            "potential": {
                "key": "866a3898-fa41-42e0-9b2c-7a25beb42604",
                "id": "1989--Tersoff-J--Si-Ge",
                "URL": "https://potentials.nist.gov/pid/rest/local/potentials/potential.1989--Tersoff-J--Si-Ge"
            }
        },
        "system-info": {
            "family": "mp-1199894",
            "family-URL": "https://potentials.nist.gov/pid/rest/local/potentials/mp-1199894",
            "parent_key": "9d926781-04e7-4d02-abb8-5670fb6d96d2",
            "symbol": "Si",
            "composition": "Si",
            "cell": {
                "crystal-family": "monoclinic",
                "natypes": 1,
                "a": 25.387875364546442,
                "b": 15.14265156401483,
                "c": 9.861688764053858,
                "alpha": 90.0,
                "beta": 94.04990379276843,
                "gamma": 90.0
            }
        },
        "atomic-system": {
            "box": {
                "avect": {
                    "value": [
                        25.387875364546442,
                        0.0,
                        0.0
                    ],
                    "unit": "angstrom"
                },
                "bvect": {
                    "value": [
                        0.0,
                        15.14265156401483,
                        0.0
                    ],
                    "unit": "angstrom"
                },
                "cvect": {
                    "value": [
                        -0.6964848358602077,
                        0.0,
                        9.837063289035141
                    ],
                    "unit": "angstrom"
                },
                "origin": {
                    "value": [
                        0.0,
                        0.0,
                        0.0
                    ],
                    "unit": "angstrom"
                }
            },
            "periodic-boundary-condition": [
                true,
                true,
                true
            ],
            "atom-type-symbol": "Si",
            "atoms": {
                "natoms": 164,
                "property": [
                    {
                        "name": "atype",
                        "data": {
                            "value": [
                                1,
                                1,
                                1,
                                1,
                                1,
                                1,
                                1,
                                1,
                                1,
                                1,
                                1,
                                1,
                                1,
                                1,
                                1,
                                1,
                                1,
                                1,
                                1,
                                1,
                                1,
                                1,
                                1,
                                1,
                                1,
                                1,
                                1,
                                1,
                                1,
                                1,
                                1,
                                1,
                                1,
                                1,
                                1,
                                1,
                                1,
                                1,
                                1,
                                1,
                                1,
                                1,
                                1,
                                1,
                                1,
                                1,
                                1,
                                1,
                                1,
                                1,
                                1,
                                1,
                                1,
                                1,
                                1,
                                1,
                                1,
                                1,
                                1,
                                1,
                                1,
                                1,
                                1,
                                1,
                                1,
                                1,
                                1,
                                1,
                                1,
                                1,
                                1,
                                1,
                                1,
                                1,
                                1,
                                1,
                                1,
                                1,
                                1,
                                1,
                                1,
                                1,
                                1,
                                1,
                                1,
                                1,
                                1,
                                1,
                                1,
                                1,
                                1,
                                1,
                                1,
                                1,
                                1,
                                1,
                                1,
                                1,
                                1,
                                1,
                                1,
                                1,
                                1,
                                1,
                                1,
                                1,
                                1,
                                1,
                                1,
                                1,
                                1,
                                1,
                                1,
                                1,
                                1,
                                1,
                                1,
                                1,
                                1,
                                1,
                                1,
                                1,
                                1,
                                1,
                                1,
                                1,
                                1,
                                1,
                                1,
                                1,
                                1,
                                1,
                                1,
                                1,
                                1,
                                1,
                                1,
                                1,
                                1,
                                1,
                                1,
                                1,
                                1,
                                1,
                                1,
                                1,
                                1,
                                1,
                                1,
                                1,
                                1,
                                1,
                                1,
                                1,
                                1,
                                1,
                                1,
                                1,
                                1,
                                1,
                                1,
                                1,
                                1,
                                1
                            ]
                        }
                    },
                    {
                        "name": "pos",
                        "data": {
                            "value": [
                                0.0,
                                0.0,
                                0.0,
                                22.14414860015263,
                                0.0,
                                6.904280588295455,
                                22.49239101808273,
                                3.0071791740975664,
                                1.9857489437778841,
                                25.039632946616337,
                                3.0071791740975664,
                                4.918531644517572,
                                1.4576042417445438,
                                0.9014193336283558,
                                9.785192454312066,
                                19.990059522547874,
                                0.9014193336283558,
                                6.9561514230185315,
                                20.33830194047798,
                                2.1057598404692106,
                                2.037619778500961,
                                1.8058466596746459,
                                2.1057598404692106,
                                4.866660809794496,
                                1.4080237584050819,
                                2.8741131234788777,
                                8.534095071086043,
                                20.03964000588734,
                                2.8741131234788777,
                                8.207248806244554,
                                20.387882423817437,
                                0.13306605061868737,
                                3.2887171617269844,
                                1.756266176335187,
                                0.13306605061868737,
                                3.6155634265684724,
                                2.2234972612303734,
                                4.767565417694815,
                                9.656582688871248,
                                19.224166503062047,
                                4.767565417694815,
                                7.084761188459349,
                                19.572408920992153,
                                13.38226532041758,
                                2.166229543941778,
                                2.571739679160478,
                                13.38226532041758,
                                4.738051044353677,
                                22.04646088722405,
                                3.1077490944602193,
                                9.446689269473087,
                                24.78907824161481,
                                3.1077490944602193,
                                7.294654607857511,
                                25.13732065954492,
                                15.042081643652176,
                                2.3761229633399408,
                                22.394703305154152,
                                15.042081643652176,
                                4.528157624955517,
                                12.907677667922108,
                                14.971176177703907,
                                1.0653342800759495,
                                21.93040861450374,
                                7.399850395696491,
                                5.838946308219508,
                                22.278651032433842,
                                10.749980342415906,
                                0.920414663701937,
                                -0.1345024322812175,
                                10.749980342415906,
                                5.983865924593521,
                                13.355398901808767,
                                13.988054667561677,
                                9.079402837450404,
                                20.78620254475687,
                                6.416728885554261,
                                7.661941039880193,
                                21.134444962686974,
                                11.733101852558134,
                                2.743409395362623,
                                1.0097036374656536,
                                11.733101852558134,
                                4.160871192932834,
                                23.30774766749485,
                                6.775897438000928,
                                1.0369641895504171,
                                24.22427629720422,
                                6.775897438000928,
                                5.8673163987450385,
                                24.572518715134326,
                                11.373933300111467,
                                0.9487847542274679,
                                22.95950524956475,
                                11.373933300111467,
                                5.955495834067988,
                                24.39923710589299,
                                5.3977722904860705,
                                7.754852102645014,
                                22.43630202294587,
                                5.3977722904860705,
                                8.986491774685584,
                                22.784544440875976,
                                12.752058447626325,
                                4.067960130168013,
                                24.747479523823092,
                                12.752058447626325,
                                2.836320458127445,
                                17.240822724180713,
                                3.2852815413965972,
                                0.04582104080035343,
                                4.903325875971915,
                                3.2852815413965972,
                                6.858459547495103,
                                5.25156829390202,
                                14.8645491967158,
                                1.9399279029775318,
                                16.8925803062506,
                                14.8645491967158,
                                4.964352685317925,
                                18.525132818567762,
                                2.0540401140520976,
                                9.808732546762718,
                                2.9225309457246573,
                                2.0540401140520976,
                                6.9326113305678785,
                                3.2707733636547625,
                                0.9531390600454673,
                                2.0140796860503074,
                                18.873375236497864,
                                0.9531390600454673,
                                4.89020090224515,
                                2.965426613768684,
                                0.09874523084885212,
                                8.207484895763459,
                                18.482237150523734,
                                0.09874523084885212,
                                8.533858981567139,
                                18.830479568453836,
                                2.908433943248713,
                                3.6153273370495693,
                                3.313669031698788,
                                2.908433943248713,
                                3.288953251245888,
                                2.601101310161872,
                                13.219194105724515,
                                7.108045517264514,
                                18.84656245413055,
                                13.219194105724515,
                                9.633298360066084,
                                19.19480487206065,
                                4.930636632387881,
                                4.714766715548512,
                                15.643281410365203,
                                12.501962414395296,
                                2.189513872746943,
                                17.219424658274864,
                                5.003139648075897,
                                8.341042704038674,
                                16.92217678829078,
                                12.574465430083311,
                                8.400301173291924,
                                4.5764815239476615,
                                13.1466910900365,
                                3.4817695287743526,
                                17.56766707620497,
                                13.1466910900365,
                                3.422511059521101,
                                4.884460675301891,
                                14.637371566626644,
                                9.432878032615307,
                                16.56320308899053,
                                14.637371566626644,
                                7.308465844715289,
                                16.911445506920636,
                                3.512459171485752,
                                2.3899342001977186,
                                17.926640775505216,
                                11.083784953493167,
                                4.514346388097737,
                                24.39716931654845,
                                12.895754639642817,
                                9.036739493965806,
                                22.438369812290414,
                                12.895754639642817,
                                7.704604383364791,
                                22.786612230220516,
                                5.254076098469578,
                                2.7860727388472206,
                                24.74541173447855,
                                5.254076098469578,
                                4.118207849448236,
                                0.8137860100481205,
                                11.854523204124002,
                                7.8446841646005945,
                                20.6338777542443,
                                11.854523204124002,
                                8.896659712730003,
                                20.982120172174405,
                                6.295307533988396,
                                3.978128068212431,
                                13.855966110251455,
                                13.86663331599581,
                                2.926152520083024,
                                13.561902650854067,
                                2.1176089653180203,
                                1.0215200001870068,
                                21.276183631571783,
                                9.688934747325435,
                                5.88276058810845,
                                8.930488367228667,
                                0.8895702087795456,
                                0.9642289435908786,
                                13.213660232923964,
                                0.8895702087795456,
                                5.940051644704577,
                                14.441798178552116,
                                2.504851993764553,
                                9.113448913493702,
                                19.699803268013525,
                                10.076177775771967,
                                7.627894963836896,
                                7.354108003670405,
                                0.5023271803330136,
                                2.709363319319325,
                                14.79004059648222,
                                0.5023271803330136,
                                4.194917268976132,
                                14.49499803524311,
                                0.4969818243306463,
                                7.868302953557483,
                                6.952665729049307,
                                0.4969818243306463,
                                8.873040923773116,
                                19.994845829252633,
                                10.081523131774334,
                                3.954509279255545,
                                14.843240453173214,
                                2.5101973497669197,
                                2.9497713090399116,
                                23.417769564419427,
                                1.4740765591506282,
                                8.370671938665298,
                                23.766011982349532,
                                1.5331026149469376,
                                3.4521402941477284,
                                12.693937682273226,
                                7.571325782007417,
                                0.0,
                                9.450210917879403,
                                7.571325782007417,
                                6.904280588295455,
                                9.798453335809507,
                                10.578504956104979,
                                1.9857489437778841,
                                12.34569526434312,
                                10.578504956104979,
                                4.918531644517572,
                                14.15154192401777,
                                8.472745115635771,
                                9.785192454312066,
                                7.296121840274657,
                                8.472745115635771,
                                6.9561514230185315,
                                7.644364258204762,
                                9.677085622476625,
                                2.037619778500961,
                                14.499784341947874,
                                9.677085622476625,
                                4.866660809794496,
                                14.10196144067831,
                                10.445438905486295,
                                8.534095071086043,
                                7.345702323614112,
                                10.445438905486295,
                                8.207248806244554,
                                7.6939447415442155,
                                7.7043918326261025,
                                3.2887171617269844,
                                14.45020385860841,
                                7.7043918326261025,
                                3.6155634265684724,
                                14.917434943503599,
                                12.33889119970223,
                                9.656582688871248,
                                6.530228820788827,
                                12.33889119970223,
                                7.084761188459349,
                                6.878471238718931,
                                5.8109395384101665,
                                2.166229543941778,
                                15.265677361433703,
                                5.8109395384101665,
                                4.738051044353677,
                                9.352523204950828,
                                10.679074876467634,
                                9.446689269473087,
                                12.095140559341594,
                                10.679074876467634,
                                7.294654607857511,
                                12.4433829772717,
                                7.4707558616447605,
                                2.3761229633399408,
                                9.700765622880931,
                                7.4707558616447605,
                                4.528157624955517,
                                0.21373998564888505,
                                7.399850395696491,
                                1.0653342800759495,
                                9.236470932230521,
                                14.971176177703907,
                                5.838946308219508,
                                9.584713350160623,
                                3.178654560408489,
                                0.920414663701937,
                                12.559435249991997,
                                3.178654560408489,
                                5.983865924593521,
                                0.6614612195355495,
                                6.416728885554261,
                                9.079402837450404,
                                8.092264862483646,
                                13.988054667561677,
                                7.661941039880193,
                                8.440507280413753,
                                4.161776070550719,
                                2.743409395362623,
                                13.703641319738871,
                                4.161776070550719,
                                4.160871192932834,
                                10.613809985221625,
                                14.347223220008344,
                                1.0369641895504171,
                                11.530338614931003,
                                14.347223220008344,
                                5.8673163987450385,
                                11.878581032861106,
                                3.8026075181040517,
                                0.9487847542274679,
                                10.265567567291523,
                                3.8026075181040517,
                                5.955495834067988,
                                11.705299423619772,
                                12.969098072493486,
                                7.754852102645014,
                                9.74236434067265,
                                12.969098072493486,
                                8.986491774685584,
                                10.090606758602751,
                                5.180732665618911,
                                4.067960130168013,
                                12.053541841549876,
                                5.180732665618911,
                                2.836320458127445,
                                4.546885041907487,
                                10.856607323404011,
                                0.04582104080035343,
                                17.597263558245142,
                                10.856607323404011,
                                6.858459547495103,
                                17.945505976175244,
                                7.293223414708384,
                                1.9399279029775318,
                                4.198642623977383,
                                7.293223414708384,
                                4.964352685317925,
                                5.831195136294539,
                                9.625365896059515,
                                9.808732546762718,
                                15.616468627997886,
                                9.625365896059515,
                                6.9326113305678785,
                                15.96471104592799,
                                8.524464842052883,
                                2.0140796860503074,
                                6.179437554224642,
                                8.524464842052883,
                                4.89020090224515,
                                15.659364296041906,
                                7.670071012856268,
                                8.207484895763459,
                                5.788299468250508,
                                7.670071012856268,
                                8.533858981567139,
                                6.136541886180615,
                                10.47975972525613,
                                3.6153273370495693,
                                16.007606713972013,
                                10.47975972525613,
                                3.288953251245888,
                                15.295038992435096,
                                5.647868323717102,
                                7.108045517264514,
                                6.152624771857326,
                                5.647868323717102,
                                9.633298360066084,
                                6.500867189787429,
                                12.501962414395296,
                                4.714766715548512,
                                2.9493437280919763,
                                4.930636632387881,
                                2.189513872746943,
                                4.525486976001639,
                                12.574465430083311,
                                8.341042704038674,
                                4.228239106017556,
                                5.003139648075897,
                                8.400301173291924,
                                17.27041920622088,
                                5.575365308029085,
                                3.4817695287743526,
                                4.873729393931745,
                                5.575365308029085,
                                3.422511059521101,
                                17.578398357575114,
                                7.066045784619228,
                                9.432878032615307,
                                3.8692654067173056,
                                7.066045784619228,
                                7.308465844715289,
                                4.217507824647411,
                                11.083784953493167,
                                2.3899342001977186,
                                5.232703093231993,
                                3.512459171485752,
                                4.514346388097737,
                                11.703231634275232,
                                5.324428857635402,
                                9.036739493965806,
                                9.74443213001719,
                                5.324428857635402,
                                7.704604383364791,
                                10.092674547947293,
                                12.825401880476994,
                                2.7860727388472206,
                                12.051474052205332,
                                12.825401880476994,
                                4.118207849448236,
                                13.507723692321349,
                                4.283197422116587,
                                7.8446841646005945,
                                7.939940071971078,
                                4.283197422116587,
                                8.896659712730003,
                                8.288182489901184,
                                13.86663331599581,
                                3.978128068212431,
                                1.162028427978228,
                                6.295307533988396,
                                2.926152520083024,
                                0.8679649685808458,
                                9.688934747325435,
                                1.0215200001870068,
                                8.582245949298557,
                                2.1176089653180203,
                                5.88276058810845,
                                21.62442604950188,
                                8.460895990786963,
                                0.9642289435908786,
                                0.5197225506507415,
                                8.460895990786963,
                                5.940051644704577,
                                1.7478604962788924,
                                10.076177775771967,
                                9.113448913493702,
                                7.005865585740304,
                                2.504851993764553,
                                7.627894963836896,
                                20.04804568594363,
                                8.07365296234043,
                                2.709363319319325,
                                2.096102914208997,
                                8.07365296234043,
                                4.194917268976132,
                                1.8010603529698868,
                                8.068307606338063,
                                7.868302953557483,
                                19.64660341132253,
                                8.068307606338063,
                                8.873040923773116,
                                7.3009081469794115,
                                2.5101973497669197,
                                3.954509279255545,
                                2.1493027708999914,
                                10.081523131774334,
                                2.9497713090399116,
                                10.72383188214621,
                                9.045402341158045,
                                8.370671938665298,
                                11.072074300076315,
                                9.104428396954352,
                                3.4521402941477284
                            ],
                            "shape": [
                                164,
                                3
                            ],
                            "unit": "angstrom"
                        }
                    }
                ]
            }
        },
        "potential-energy": {
            "value": -4.485520429224451,
            "unit": "eV"
        },
        "cohesive-energy": {
            "value": -4.485520429224451,
            "unit": "eV"
        }
    }
}