{
    "relaxed-crystal": {
        "key": "ff11dd34-d130-463a-8458-085ed90fec0e",
        "URL": "https://potentials.nist.gov/pid/rest/local/potentials/ff11dd34-d130-463a-8458-085ed90fec0e",
        "method": "static",
        "standing": "bad",
        "potential-LAMMPS": {
            "key": "MO_826591359508_000",
            "id": "EAM_Dynamo_PunYamakovMishin_2013_NiAlCo__MO_826591359508_000",
            "URL": "https://potentials.nist.gov/pid/rest/local/potentials/MO_826591359508",
            "potential": {
                "key": "0f6e3cef-c588-4dcb-a0a6-66878f64ac50",
                "id": "2015--Purja-Pun-G-P-Yamakov-V-Mishin-Y--Ni-Al-Co",
                "URL": "https://potentials.nist.gov/pid/rest/local/potentials/potential.2015--Purja-Pun-G-P-Yamakov-V-Mishin-Y--Ni-Al-Co"
            }
        },
        "system-info": {
            "family": "A3'--alpha-La--double-hcp",
            "family-URL": "https://potentials.nist.gov/pid/rest/local/potentials/A3'--alpha-La--double-hcp",
            "parent_key": "5fec0c9d-db00-4d17-842b-93dfac4af73d",
            "symbol": "Ni",
            "composition": "Ni",
            "cell": {
                "crystal-family": "hexagonal",
                "natypes": 1,
                "a": 5.199999999999999,
                "b": 5.199999999999999,
                "c": 16.9831288832972,
                "alpha": 90.0,
                "beta": 90.0,
                "gamma": 120.00000000000001
            }
        },
        "atomic-system": {
            "box": {
                "avect": {
                    "value": [
                        5.199999999999999,
                        0.0,
                        0.0
                    ],
                    "unit": "angstrom"
                },
                "bvect": {
                    "value": [
                        -2.600000000000001,
                        4.5033320996790795,
                        0.0
                    ],
                    "unit": "angstrom"
                },
                "cvect": {
                    "value": [
                        0.0,
                        0.0,
                        16.9831288832972
                    ],
                    "unit": "angstrom"
                },
                "origin": {
                    "value": [
                        0.0,
                        0.0,
                        0.0
                    ],
                    "unit": "angstrom"
                }
            },
            "periodic-boundary-condition": [
                true,
                true,
                true
            ],
            "atom-type-symbol": "Ni",
            "atoms": {
                "natoms": 4,
                "property": [
                    {
                        "name": "atype",
                        "data": {
                            "value": [
                                1,
                                1,
                                1,
                                1
                            ]
                        }
                    },
                    {
                        "name": "pos",
                        "data": {
                            "value": [
                                0.0,
                                0.0,
                                0.0,
                                0.0,
                                0.0,
                                8.4915644416486,
                                -2.220446049250313e-16,
                                3.0022213997860523,
                                4.2457822208243,
                                2.5999999999999996,
                                1.5011106998930264,
                                12.737346662472904
                            ],
                            "shape": [
                                4,
                                3
                            ],
                            "unit": "angstrom"
                        }
                    }
                ]
            }
        },
        "potential-energy": {
            "value": -2.773995146916e-30,
            "unit": "eV"
        },
        "cohesive-energy": {
            "value": -2.773995146916e-30,
            "unit": "eV"
        }
    }
}